LICENSE
README.rst
setup.cfg
setup.py
restructuredWeb/__init__.py
restructuredWeb/adsense.py
restructuredWeb/codepen.py
restructuredWeb/configuration_block.py
restructuredWeb/css.py
restructuredWeb/gist.py
restructuredWeb/javascript.py
restructuredWeb/jsfiddle.py
restructuredWeb/layout.py
restructuredWeb/ted.py
restructuredWeb/twitter.py
restructuredWeb/youtube.py
restructuredWeb.egg-info/PKG-INFO
restructuredWeb.egg-info/SOURCES.txt
restructuredWeb.egg-info/dependency_links.txt
restructuredWeb.egg-info/not-zip-safe
restructuredWeb.egg-info/requires.txt
restructuredWeb.egg-info/top_level.txt
tests/testapps/__init__.py
tests/testapps/html/__init__.py
tests/testapps/html/conf.py
tests/testapps/slides/__init__.py
tests/testapps/slides/conf.py