Metadata-Version: 1.1
Name: restructuredWeb
Version: 1.0.0
Summary: Web directives for use with Sphinx.
Home-page: https://github.com/lakhman/restructuredWeb
Author: Anil Lakhman
Author-email: restructured.web@anil.io
License: The MIT License
